odoo/addons/product_category_product_link/README.rst
odoo/addons/product_category_product_link/__init__.py
odoo/addons/product_category_product_link/__manifest__.py
odoo/addons/product_category_product_link/i18n/ca.po
odoo/addons/product_category_product_link/i18n/it.po
odoo/addons/product_category_product_link/i18n/product_category_product_link.pot
odoo/addons/product_category_product_link/models/__init__.py
odoo/addons/product_category_product_link/models/product_category.py
odoo/addons/product_category_product_link/models/product_template.py
odoo/addons/product_category_product_link/readme/CONTRIBUTORS.md
odoo/addons/product_category_product_link/readme/DESCRIPTION.md
odoo/addons/product_category_product_link/static/description/icon.png
odoo/addons/product_category_product_link/static/description/index.html
odoo_addon_product_category_product_link-18.0.1.0.0.2.dist-info/METADATA
odoo_addon_product_category_product_link-18.0.1.0.0.2.dist-info/WHEEL
odoo_addon_product_category_product_link-18.0.1.0.0.2.dist-info/top_level.txt
odoo_addon_product_category_product_link-18.0.1.0.0.2.dist-info/RECORD
